LICENSE
MANIFEST.in
README.md
pyproject.toml
requirements.txt
setup.py
dicom_csv/__init__.py
dicom_csv/__version__.py
dicom_csv/aggregation.py
dicom_csv/convert.py
dicom_csv/crawler.py
dicom_csv/exceptions.py
dicom_csv/interface.py
dicom_csv/misc.py
dicom_csv/rtstruct.py
dicom_csv/scripts.py
dicom_csv/spatial.py
dicom_csv/tags.py
dicom_csv/utils.py
dicom_csv.egg-info/PKG-INFO
dicom_csv.egg-info/SOURCES.txt
dicom_csv.egg-info/dependency_links.txt
dicom_csv.egg-info/entry_points.txt
dicom_csv.egg-info/requires.txt
dicom_csv.egg-info/top_level.txt
tests/test_file_operations.py
tests/test_spatial.py