Metadata-Version: 2.4
Name: dicom_csv
Version: 0.4.0
Summary: Utils for gathering, aggregation and handling metadata from DICOM files.
Home-page: https://github.com/neuro-ml/dicom-csv
Download-URL: https://github.com/neuro-ml/dicom-csv/v0.4.0.tar.gz
Author-email: NeuroML Group <max@ira-labs.com>
License: MIT License
Project-URL: Homepage, https://github.com/neuro-ml/dicom_csv
Project-URL: Issues, https://github.com/neuro-ml/dicom_csv/issues
Project-URL: Source, https://github.com/neuro-ml/dicom_csv
Project-URL: Docs, https://dicom-csv.readthedocs.io/en/latest/index.html
Keywords: DICOM
Classifier: Development Status :: 4 - Beta
Classifier: License :: OSI Approved :: MIT License
Classifier: Programming Language :: Python :: 3
Classifier: Programming Language :: Python :: 3.7
Classifier: Programming Language :: Python :: 3.8
Classifier: Programming Language :: Python :: 3.9
Classifier: Programming Language :: Python :: 3.10
Classifier: Programming Language :: Python :: 3.11
Classifier: Programming Language :: Python :: 3.12
Classifier: Programming Language :: Python :: 3 :: Only
Requires-Python: >=3.7
License-File: LICENSE
Requires-Dist: pydicom<4.0,>=3.0
Requires-Dist: pandas
Requires-Dist: numpy
Requires-Dist: tqdm
Requires-Dist: more_itertools
Provides-Extra: nifti
Requires-Dist: nibabel; extra == "nifti"
Provides-Extra: all
Requires-Dist: nibabel; extra == "all"
Dynamic: download-url
Dynamic: home-page
Dynamic: license-file
Dynamic: requires-python
